{
  "hour": {
    "topSiteHits": [
      {
        "hits": "2",
        "url": "/index.xml"
      },
      {
        "hits": "1",
        "url": "/"
      },
      {
        "hits": "1",
        "url": "/highlight/index.xml"
      },
      {
        "hits": "1",
        "url": "/note/index.xml"
      },
      {
        "hits": "1",
        "url": "/photo/index.xml"
      },
      {
        "hits": "1",
        "url": "/tags/running/"
      }
    ],
    "topSiteMisses": [],
    "topApiHits": [
      {
        "hits": "12",
        "url": "/analytics"
      },
      {
        "hits": "12",
        "url": "/articles?limit=5000"
      },
      {
        "hits": "11",
        "url": "/books/reading?limit=5000"
      },
      {
        "hits": "11",
        "url": "/books/read?limit=5000"
      },
      {
        "hits": "11",
        "url": "/books/toread?limit=5000"
      },
      {
        "hits": "11",
        "url": "/films/towatch?limit=5000"
      },
      {
        "hits": "11",
        "url": "/films/watched?limit=5000"
      },
      {
        "hits": "11",
        "url": "/pocket?limit=5000"
      }
    ],
    "totalSiteHits": [
      {
        "hits": "7"
      }
    ],
    "totalApiHits": [
      {
        "hits": "90"
      }
    ]
  },
  "day": {
    "topSiteHits": [
      {
        "hits": "46",
        "url": "/index.xml"
      },
      {
        "hits": "32",
        "url": "/highlight/minneapolis-disband-police/"
      },
      {
        "hits": "26",
        "url": "/photo/index.xml"
      },
      {
        "hits": "24",
        "url": "/highlight/index.xml"
      },
      {
        "hits": "24",
        "url": "/note/index.xml"
      },
      {
        "hits": "10",
        "url": "/"
      },
      {
        "hits": "8",
        "url": "/open-graph.png"
      },
      {
        "hits": "5",
        "url": "/work/"
      },
      {
        "hits": "5",
        "url": "/favicon.png"
      },
      {
        "hits": "5",
        "url": "/css/style.css"
      },
      {
        "hits": "4",
        "url": "/post/activist-relief-resources/"
      },
      {
        "hits": "3",
        "url": "/tags/history/"
      },
      {
        "hits": "3",
        "url": "/articles/saved/"
      },
      {
        "hits": "2",
        "url": "/highlight/neofeudalism-larb/"
      },
      {
        "hits": "2",
        "url": "/highlight/names-gender-code/"
      },
      {
        "hits": "2",
        "url": "/highlight/roxane-gay-cleaner/"
      },
      {
        "hits": "2",
        "url": "/highlight/tulip-farm-covid/"
      },
      {
        "hits": "2",
        "url": "/media/"
      },
      {
        "hits": "2",
        "url": "/rss/"
      },
      {
        "hits": "2",
        "url": "/highlight/ronan-farrow-too-good/"
      },
      {
        "hits": "2",
        "url": "/tags/love/index.xml"
      },
      {
        "hits": "2",
        "url": "/highlight/chat-roulette-quar/"
      },
      {
        "hits": "2",
        "url": "/note/2020-05-28t09-04-31/"
      },
      {
        "hits": "2",
        "url": "/share/share-utils.js"
      },
      {
        "hits": "1",
        "url": "/highlight/bridgers-rolling-stone/"
      },
      {
        "hits": "1",
        "url": "/highlight/negroni-season/"
      },
      {
        "hits": "1",
        "url": "/highlight/animal-crossing-interest-rates/"
      },
      {
        "hits": "1",
        "url": "/books/toread/"
      },
      {
        "hits": "1",
        "url": "/highlight/new-york-geology/"
      },
      {
        "hits": "1",
        "url": "/highlight/no-more-buying-stuff/"
      },
      {
        "hits": "1",
        "url": "/highlight/mouse-feeder-welfare/"
      },
      {
        "hits": "1",
        "url": "/highlight/american-police-departments/"
      },
      {
        "hits": "1",
        "url": "/note/2020-01-27iranian-shootdown-coverup/"
      },
      {
        "hits": "1",
        "url": "/note/2020-01-02-04-coronavirus-central-lockdown/"
      },
      {
        "hits": "1",
        "url": "/highlight/london-bikes-covid/"
      },
      {
        "hits": "1",
        "url": "/highlight/american-girl-doll-history/"
      },
      {
        "hits": "1",
        "url": "/analytics/week/"
      },
      {
        "hits": "1",
        "url": "/highlight/lbj-movies/"
      },
      {
        "hits": "1",
        "url": "/highlight/larry-kramer-obit/"
      },
      {
        "hits": "1",
        "url": "/films/watched/"
      },
      {
        "hits": "1",
        "url": "/journal/"
      },
      {
        "hits": "1",
        "url": "/highlight/world-without-cops/"
      },
      {
        "hits": "1",
        "url": "/journal/2020-03-21/"
      },
      {
        "hits": "1",
        "url": "/link/index.xml"
      },
      {
        "hits": "1",
        "url": "/highlight/la-haine-society/"
      },
      {
        "hits": "1",
        "url": "/note/"
      },
      {
        "hits": "1",
        "url": "/articles/liked/"
      },
      {
        "hits": "1",
        "url": "/note/2020-01-11-contrecoup/"
      },
      {
        "hits": "1",
        "url": "/highlight/the-american-room/"
      },
      {
        "hits": "1",
        "url": "/highlight/snowden-gellman/"
      }
    ],
    "topSiteMisses": [],
    "topApiHits": [
      {
        "hits": "288",
        "url": "/analytics"
      },
      {
        "hits": "287",
        "url": "/articles?limit=5000"
      },
      {
        "hits": "287",
        "url": "/books/reading?limit=5000"
      },
      {
        "hits": "287",
        "url": "/books/read?limit=5000"
      },
      {
        "hits": "287",
        "url": "/books/toread?limit=5000"
      },
      {
        "hits": "287",
        "url": "/films/towatch?limit=5000"
      },
      {
        "hits": "287",
        "url": "/films/watched?limit=5000"
      },
      {
        "hits": "287",
        "url": "/pocket?limit=5000"
      },
      {
        "hits": "2",
        "url": "/"
      }
    ],
    "totalSiteHits": [
      {
        "hits": "303"
      }
    ],
    "totalApiHits": [
      {
        "hits": "2299"
      }
    ]
  },
  "week": {
    "topSiteHits": [
      {
        "hits": "316",
        "url": "/index.xml"
      },
      {
        "hits": "175",
        "url": "/photo/index.xml"
      },
      {
        "hits": "170",
        "url": "/note/index.xml"
      },
      {
        "hits": "168",
        "url": "/highlight/index.xml"
      },
      {
        "hits": "91",
        "url": "/"
      },
      {
        "hits": "75",
        "url": "/open-graph.png"
      },
      {
        "hits": "52",
        "url": "/css/style.css"
      },
      {
        "hits": "41",
        "url": "/favicon.png"
      },
      {
        "hits": "39",
        "url": "/post/activist-relief-resources/"
      },
      {
        "hits": "32",
        "url": "/highlight/minneapolis-disband-police/"
      },
      {
        "hits": "23",
        "url": "/articles/saved/"
      },
      {
        "hits": "17",
        "url": "/post/"
      },
      {
        "hits": "16",
        "url": "/work/"
      },
      {
        "hits": "14",
        "url": "/highlight/"
      },
      {
        "hits": "12",
        "url": "/note/"
      },
      {
        "hits": "10",
        "url": "/journal/"
      },
      {
        "hits": "10",
        "url": "/media/"
      },
      {
        "hits": "9",
        "url": "/post/getting-of-of-netlify/"
      },
      {
        "hits": "8",
        "url": "/tags/news/"
      },
      {
        "hits": "8",
        "url": "/tags/politics/"
      },
      {
        "hits": "8",
        "url": "/films/watched/"
      },
      {
        "hits": "8",
        "url": "/elsewhere/"
      },
      {
        "hits": "7",
        "url": "/tags/science/"
      },
      {
        "hits": "7",
        "url": "/books/reading/"
      },
      {
        "hits": "7",
        "url": "/tags/tech/"
      },
      {
        "hits": "7",
        "url": "/tags/accessibility/"
      },
      {
        "hits": "7",
        "url": "/tags/internet/"
      },
      {
        "hits": "7",
        "url": "/tags/poetry/"
      },
      {
        "hits": "7",
        "url": "/rss/"
      },
      {
        "hits": "7",
        "url": "/post/how-this-site-works/"
      },
      {
        "hits": "6",
        "url": "/highlight/lbj-movies/"
      },
      {
        "hits": "6",
        "url": "/journal/2020-04-12/"
      },
      {
        "hits": "6",
        "url": "/highlight/ronan-farrow-too-good/"
      },
      {
        "hits": "6",
        "url": "/highlight/snowden-gellman/"
      },
      {
        "hits": "6",
        "url": "/post/2018-09-04-its-you-and-me/"
      },
      {
        "hits": "6",
        "url": "/analytics/day/"
      },
      {
        "hits": "6",
        "url": "/highlight/covid-19-virus-profile/"
      },
      {
        "hits": "6",
        "url": "/link/"
      },
      {
        "hits": "6",
        "url": "/tags/love/"
      },
      {
        "hits": "6",
        "url": "/tags/history/"
      },
      {
        "hits": "6",
        "url": "/tags/funny/"
      },
      {
        "hits": "6",
        "url": "/tags/book/"
      },
      {
        "hits": "6",
        "url": "/tags/food/"
      },
      {
        "hits": "5",
        "url": "/books/toread/"
      },
      {
        "hits": "5",
        "url": "/post/2016-05-05-fat-internet-historian/"
      },
      {
        "hits": "5",
        "url": "/articles/liked/"
      },
      {
        "hits": "5",
        "url": "/post/2015-03-02-internet-rhizome/"
      },
      {
        "hits": "5",
        "url": "/post/2016-08-22-that-accessibility-thing/"
      },
      {
        "hits": "5",
        "url": "/highlight/negroni-season/"
      },
      {
        "hits": "5",
        "url": "/highlight/mother-board-earth/"
      }
    ],
    "topSiteMisses": [
      {
        "hits": "96",
        "url": "/robots.txt"
      },
      {
        "hits": "3",
        "url": "/photo/south-india/images/IMG_2251_hu1ddaec928864e2ac7f3bc7f0b4820fb9_285959_800x0_resize_q75_box.jpg"
      },
      {
        "hits": "3",
        "url": "/photo/south-india/images/IMG_1852_hufdcdb9ce05456e41ca5036f054c92962_98358_800x0_resize_q75_box.jpg"
      },
      {
        "hits": "2",
        "url": "/photo/south-india/images/IMG_2421_hu1ddaec928864e2ac7f3bc7f0b4820fb9_231897_800x0_resize_q75_box.jpg"
      },
      {
        "hits": "2",
        "url": "/photo/south-india/images/IMG_1699_hu75886160133b06c1644ee6ee3cc8c02b_188186_800x0_resize_q75_box.jpg"
      },
      {
        "hits": "2",
        "url": "/photo/norfolk-shore/images/IMG_0075_huacd9e7f664faafd3b06dcbe4afe43fa1_2459407_800x0_resize_q75_box.jpg"
      },
      {
        "hits": "2",
        "url": "/photo/south-india/images/IMG_1796_hu1ddaec928864e2ac7f3bc7f0b4820fb9_170352_800x0_resize_q75_box.jpg"
      },
      {
        "hits": "2",
        "url": "/photo/ben-nevis/images/IMG_0038_huad381fb499f2badc1d9f5391a18539b4_1464347_800x0_resize_q75_box.jpg"
      },
      {
        "hits": "2",
        "url": "/photo/norfolk-shore/images/IMG_9978_huacd9e7f664faafd3b06dcbe4afe43fa1_1546654_800x0_resize_q75_box.jpg"
      },
      {
        "hits": "2",
        "url": "/photo/south-india/images/IMG_2603_hu041a2f3f6cbbc1fd9d6ab0db6c716ed2_157548_800x0_resize_q75_box.jpg"
      },
      {
        "hits": "2",
        "url": "/photo/south-india/images/IMG_1981_hufdcdb9ce05456e41ca5036f054c92962_442576_800x0_resize_q75_box.jpg"
      },
      {
        "hits": "2",
        "url": "/photo/south-india/images/IMG_1997_hu737147df5fde39d335039aa0fd05e9e4_63216_800x0_resize_q75_box.jpg"
      },
      {
        "hits": "2",
        "url": "/photo/south-india/images/IMG_2811_hu4aaa7c1a3e8323c6d4b8241fc16dfb02_614686_800x0_resize_q75_box.jpg"
      },
      {
        "hits": "2",
        "url": "/photo/south-india/images/IMG_2865_hu4aaa7c1a3e8323c6d4b8241fc16dfb02_442353_800x0_resize_q75_box.jpg"
      },
      {
        "hits": "2",
        "url": "/photo/south-india/images/IMG_2893_hu4aaa7c1a3e8323c6d4b8241fc16dfb02_339748_800x0_resize_q75_box.jpg"
      },
      {
        "hits": "2",
        "url": "/wp-login.php"
      },
      {
        "hits": "2",
        "url": "/photo/south-india/images/IMG_2922_hu4aaa7c1a3e8323c6d4b8241fc16dfb02_320966_800x0_resize_q75_box.jpg"
      },
      {
        "hits": "2",
        "url": "/photo/south-india/images/IMG_2947_hu4aaa7c1a3e8323c6d4b8241fc16dfb02_324773_800x0_resize_q75_box.jpg"
      },
      {
        "hits": "2",
        "url": "/photo/south-india/images/IMG_2002_hu737147df5fde39d335039aa0fd05e9e4_613917_800x0_resize_q75_box.jpg"
      },
      {
        "hits": "2",
        "url": "/note/avalanche-school/"
      },
      {
        "hits": "2",
        "url": "/note/dawn-or-dusk-painting/"
      },
      {
        "hits": "2",
        "url": "/note/joe-biden-stutter/"
      },
      {
        "hits": "2",
        "url": "/photo/south-india/images/IMG_2208_hu737147df5fde39d335039aa0fd05e9e4_163211_800x0_resize_q75_box.jpg"
      },
      {
        "hits": "1",
        "url": "/photo/ben-nevis/images/IMG_0030_huad381fb499f2badc1d9f5391a18539b4_497197_800x0_resize_q75_box.jpg"
      },
      {
        "hits": "1",
        "url": "/photo/ben-nevis/images/IMG_0044_huad381fb499f2badc1d9f5391a18539b4_672587_800x0_resize_q75_box.jpg"
      },
      {
        "hits": "1",
        "url": "/photo/budapest"
      },
      {
        "hits": "1",
        "url": "/photo/grand-canyon"
      },
      {
        "hits": "1",
        "url": "/photo/isle-of-skye/images/IMG_0078_huad381fb499f2badc1d9f5391a18539b4_1174123_800x0_resize_q75_box.jpg"
      },
      {
        "hits": "1",
        "url": "/photo/loch-lomond/images/IMG_0008_huad381fb499f2badc1d9f5391a18539b4_1313177_800x0_resize_q75_box.jpg"
      },
      {
        "hits": "1",
        "url": "/photo/norfolk-shore/images/IMG_0042_huacd9e7f664faafd3b06dcbe4afe43fa1_1337252_800x0_resize_q75_box.jpg"
      },
      {
        "hits": "1",
        "url": "/photo/norfolk-shore/images/IMG_0045_huacd9e7f664faafd3b06dcbe4afe43fa1_939044_800x0_resize_q75_box.jpg"
      },
      {
        "hits": "1",
        "url": "/photo/norfolk-shore/images/IMG_0154_huacd9e7f664faafd3b06dcbe4afe43fa1_912108_800x0_resize_q75_box.jpg"
      },
      {
        "hits": "1",
        "url": "/photo/norfolk-shore/images/norfolk-shore_hu47d2b59afb0338b498b7baf30c736f78_740104_800x0_resize_q75_box.jpg"
      },
      {
        "hits": "1",
        "url": "/photos/edinburgh"
      },
      {
        "hits": "1",
        "url": "/photos/los-angeles"
      },
      {
        "hits": "1",
        "url": "/photo/south-india/images/IMG_1723_hu75886160133b06c1644ee6ee3cc8c02b_145287_800x0_resize_q75_box.jpg"
      },
      {
        "hits": "1",
        "url": "/photo/south-india/images/IMG_1827_hu74b9c62dde200713bb1748bb01fde650_244432_800x0_resize_q75_box.jpg"
      },
      {
        "hits": "1",
        "url": "/photo/south-india/images/IMG_1944_hu737147df5fde39d335039aa0fd05e9e4_240287_800x0_resize_q75_box.jpg"
      },
      {
        "hits": "1",
        "url": "/photo/south-india/images/IMG_2103_hu737147df5fde39d335039aa0fd05e9e4_349470_800x0_resize_q75_box.jpg"
      },
      {
        "hits": "1",
        "url": "/photo/south-india/images/IMG_2111_hu737147df5fde39d335039aa0fd05e9e4_237411_800x0_resize_q75_box.jpg"
      },
      {
        "hits": "1",
        "url": "/photo/south-india/images/IMG_2129_hu737147df5fde39d335039aa0fd05e9e4_614796_800x0_resize_q75_box.jpg"
      },
      {
        "hits": "1",
        "url": "/photo/south-india/images/IMG_2453_hu1ddaec928864e2ac7f3bc7f0b4820fb9_137128_800x0_resize_q75_box.jpg"
      },
      {
        "hits": "1",
        "url": "/photo/south-india/images/IMG_2481_hu1ddaec928864e2ac7f3bc7f0b4820fb9_403338_800x0_resize_q75_box.jpg"
      },
      {
        "hits": "1",
        "url": "/photo/south-india/images/IMG_2505_hu1ddaec928864e2ac7f3bc7f0b4820fb9_372234_800x0_resize_q75_box.jpg"
      },
      {
        "hits": "1",
        "url": "/photo/south-india/images/IMG_2538_hu1ddaec928864e2ac7f3bc7f0b4820fb9_255996_800x0_resize_q75_box.jpg"
      },
      {
        "hits": "1",
        "url": "/photo/south-india/images/IMG_2548_hu1ddaec928864e2ac7f3bc7f0b4820fb9_374159_800x0_resize_q75_box.jpg"
      },
      {
        "hits": "1",
        "url": "/photo/south-india/images/IMG_2584_hudc2151d3367441da7d4037ec8f2bceb0_102968_800x0_resize_q75_box.jpg"
      },
      {
        "hits": "1",
        "url": "/photo/south-india/images/IMG_2631_hu09d7ec24e360cb59a358c08f001aab08_167294_800x0_resize_q75_box.jpg"
      },
      {
        "hits": "1",
        "url": "/photo/south-india/images/IMG_2697_hu4aaa7c1a3e8323c6d4b8241fc16dfb02_376666_800x0_resize_q75_box.jpg"
      },
      {
        "hits": "1",
        "url": "/photo/south-india/images/IMG_3003_hu4aaa7c1a3e8323c6d4b8241fc16dfb02_221785_800x0_resize_q75_box.jpg"
      }
    ],
    "topApiHits": [
      {
        "hits": "2016",
        "url": "/articles?limit=5000"
      },
      {
        "hits": "2016",
        "url": "/films/towatch?limit=5000"
      },
      {
        "hits": "2016",
        "url": "/films/watched?limit=5000"
      },
      {
        "hits": "2016",
        "url": "/analytics"
      },
      {
        "hits": "2016",
        "url": "/pocket?limit=5000"
      },
      {
        "hits": "2015",
        "url": "/books/read?limit=5000"
      },
      {
        "hits": "2015",
        "url": "/books/reading?limit=5000"
      },
      {
        "hits": "2015",
        "url": "/books/toread?limit=5000"
      },
      {
        "hits": "10",
        "url": "/"
      }
    ],
    "totalSiteHits": [
      {
        "hits": "2081"
      }
    ],
    "totalApiHits": [
      {
        "hits": "16135"
      }
    ]
  },
  "month": {
    "topSiteHits": [
      {
        "hits": "1621",
        "url": "/note/index.xml"
      },
      {
        "hits": "1270",
        "url": "/index.xml"
      },
      {
        "hits": "749",
        "url": "/highlight/index.xml"
      },
      {
        "hits": "693",
        "url": "/open-graph.png"
      },
      {
        "hits": "674",
        "url": "/photo/index.xml"
      },
      {
        "hits": "582",
        "url": "/post/index.xml"
      },
      {
        "hits": "576",
        "url": "/"
      },
      {
        "hits": "315",
        "url": "/css/style.css"
      },
      {
        "hits": "242",
        "url": "/favicon.png"
      },
      {
        "hits": "122",
        "url": "/post/activist-relief-resources/"
      },
      {
        "hits": "81",
        "url": "/note/"
      },
      {
        "hits": "79",
        "url": "/post/"
      },
      {
        "hits": "68",
        "url": "/articles/saved/"
      },
      {
        "hits": "58",
        "url": "/work/"
      },
      {
        "hits": "57",
        "url": "/highlight/covid-urbanist-fantasies/"
      },
      {
        "hits": "55",
        "url": "/highlight/mother-board-earth/"
      },
      {
        "hits": "55",
        "url": "/journal/"
      },
      {
        "hits": "53",
        "url": "/highlight/bring-back-blogs/"
      },
      {
        "hits": "51",
        "url": "/highlight/roxane-gay-cleaner/"
      },
      {
        "hits": "51",
        "url": "/highlight/"
      },
      {
        "hits": "49",
        "url": "/media/"
      },
      {
        "hits": "49",
        "url": "/highlight/snowden-gellman/"
      },
      {
        "hits": "49",
        "url": "/highlight/tfl-streetspace/"
      },
      {
        "hits": "49",
        "url": "/highlight/robert-pattinson/"
      },
      {
        "hits": "48",
        "url": "/highlight/chat-roulette-quar/"
      },
      {
        "hits": "48",
        "url": "/post/getting-of-of-netlify/"
      },
      {
        "hits": "45",
        "url": "/rss/"
      },
      {
        "hits": "45",
        "url": "/highlight/tulip-farm-covid/"
      },
      {
        "hits": "45",
        "url": "/highlight/american-girl-doll-history/"
      },
      {
        "hits": "45",
        "url": "/highlight/covid-flour-surge/"
      },
      {
        "hits": "45",
        "url": "/highlight/la-haine-society/"
      },
      {
        "hits": "44",
        "url": "/highlight/coronavirus-city-sound/"
      },
      {
        "hits": "43",
        "url": "/highlight/human-scale-cities/"
      },
      {
        "hits": "43",
        "url": "/highlight/trump-covid-meltdown/"
      },
      {
        "hits": "42",
        "url": "/highlight/names-gender-code/"
      },
      {
        "hits": "42",
        "url": "/highlight/london-bikes-covid/"
      },
      {
        "hits": "42",
        "url": "/highlight/ronan-farrow-too-good/"
      },
      {
        "hits": "41",
        "url": "/highlight/cessna-badass-plane/"
      },
      {
        "hits": "40",
        "url": "/highlight/mouse-feeder-welfare/"
      },
      {
        "hits": "40",
        "url": "/highlight/new-york-geology/"
      },
      {
        "hits": "38",
        "url": "/highlight/off-road-land-trains/"
      },
      {
        "hits": "38",
        "url": "/highlight/skye-covid-home/"
      },
      {
        "hits": "37",
        "url": "/highlight/samin-nosrat-eating/"
      },
      {
        "hits": "37",
        "url": "/highlight/alison-roman-culture/"
      },
      {
        "hits": "37",
        "url": "/books/reading/"
      },
      {
        "hits": "36",
        "url": "/highlight/american-police-departments/"
      },
      {
        "hits": "36",
        "url": "/analytics/day/"
      },
      {
        "hits": "36",
        "url": "/highlight/no-more-buying-stuff/"
      },
      {
        "hits": "36",
        "url": "/highlight/reading-in-the-dark/"
      },
      {
        "hits": "35",
        "url": "/highlight/ford-best-games/"
      }
    ],
    "topSiteMisses": [
      {
        "hits": "1035",
        "url": "/robots.txt"
      },
      {
        "hits": "307",
        "url": "/sw.js"
      },
      {
        "hits": "50",
        "url": "/favicon.ico"
      },
      {
        "hits": "44",
        "url": "/note/corona-nyc-hospitals/"
      },
      {
        "hits": "28",
        "url": "/note/animal-crossing-labour/"
      },
      {
        "hits": "21",
        "url": "/note/2020-04-27t104500.315z/"
      },
      {
        "hits": "20",
        "url": "/note/moses-long-island-klan/"
      },
      {
        "hits": "19",
        "url": "/jackreid.xyz/css/style.css"
      },
      {
        "hits": "15",
        "url": "/photo/ben-nevis/"
      },
      {
        "hits": "14",
        "url": "/note/dawn-or-dusk-painting/"
      },
      {
        "hits": "13",
        "url": "/wp-login.php"
      },
      {
        "hits": "12",
        "url": "/note/tech-sabbath/"
      },
      {
        "hits": "12",
        "url": "/photo/norfolk-shore/"
      },
      {
        "hits": "12",
        "url": "/note/2010-lists/"
      },
      {
        "hits": "12",
        "url": "/note/aristophanes-wasps/"
      },
      {
        "hits": "12",
        "url": "/note/roman-silphium/"
      },
      {
        "hits": "11",
        "url": "/photo/loch-lomond/"
      },
      {
        "hits": "11",
        "url": "/note/there-is-no-outside/"
      },
      {
        "hits": "10",
        "url": "/note/eugenics-statistics/"
      },
      {
        "hits": "10",
        "url": "/phpMyAdmin/scripts/setup.php"
      },
      {
        "hits": "10",
        "url": "/note/there-is-so-swing-voter/"
      },
      {
        "hits": "10",
        "url": "/note/coronavirus-central-lockdown/"
      },
      {
        "hits": "10",
        "url": "/note/carlos-williams-love/"
      },
      {
        "hits": "10",
        "url": "/note/bob-fosse/"
      },
      {
        "hits": "10",
        "url": "/note/screen-protectors/"
      },
      {
        "hits": "10",
        "url": "/note/avalanche-school/"
      },
      {
        "hits": "10",
        "url": "/note/willard-maps-of-time/"
      },
      {
        "hits": "10",
        "url": "/post/getting-of-off-netlify"
      },
      {
        "hits": "10",
        "url": "/note/james-joyce-estate/"
      },
      {
        "hits": "9",
        "url": "/note/duchy-of-cornwall/"
      },
      {
        "hits": "9",
        "url": "/note/driving-school/"
      },
      {
        "hits": "9",
        "url": "/note/precariously-balanced-rocks/"
      },
      {
        "hits": "9",
        "url": "/note/reading-difficult-books/"
      },
      {
        "hits": "9",
        "url": "/note/plath-vs-hughes/"
      },
      {
        "hits": "9",
        "url": "/note/uss-fitzgerald/"
      },
      {
        "hits": "9",
        "url": "/note/joe-biden-stutter/"
      },
      {
        "hits": "9",
        "url": "/login?from=0.000000"
      },
      {
        "hits": "9",
        "url": "/note/senate-impeachment-hamilton/"
      },
      {
        "hits": "9",
        "url": "/note/untranslatable-words/"
      },
      {
        "hits": "9",
        "url": "/phpmyadmin/scripts/setup.php"
      },
      {
        "hits": "9",
        "url": "/note/tools-i-wish-existed/"
      },
      {
        "hits": "8",
        "url": "/note/files-going-extinct/"
      },
      {
        "hits": "8",
        "url": "/note/pearshaped-magazine-archive/"
      },
      {
        "hits": "8",
        "url": "/note/rise-of-the-blur/"
      },
      {
        "hits": "8",
        "url": "/note/contrecoup/"
      },
      {
        "hits": "8",
        "url": "/note/the-great-regression/"
      },
      {
        "hits": "8",
        "url": "/photo/south-india/"
      },
      {
        "hits": "8",
        "url": "/jackreid.xyz/favicon.png"
      },
      {
        "hits": "8",
        "url": "/note/madame-tussaud/"
      },
      {
        "hits": "8",
        "url": "/photo/the-trossachs/"
      }
    ],
    "topApiHits": [
      {
        "hits": "7736",
        "url": "/pocket?limit=5000"
      },
      {
        "hits": "7736",
        "url": "/books/toread?limit=5000"
      },
      {
        "hits": "7736",
        "url": "/films/towatch?limit=5000"
      },
      {
        "hits": "7736",
        "url": "/films/watched?limit=5000"
      },
      {
        "hits": "7736",
        "url": "/articles?limit=5000"
      },
      {
        "hits": "7736",
        "url": "/books/reading?limit=5000"
      },
      {
        "hits": "7736",
        "url": "/books/read?limit=5000"
      },
      {
        "hits": "7416",
        "url": "/analytics"
      },
      {
        "hits": "30",
        "url": "/"
      },
      {
        "hits": "4",
        "url": "/books/reading"
      }
    ],
    "totalSiteHits": [
      {
        "hits": "12399"
      }
    ],
    "totalApiHits": [
      {
        "hits": "61602"
      }
    ]
  },
  "year": {
    "topSiteHits": [
      {
        "hits": "1621",
        "url": "/note/index.xml"
      },
      {
        "hits": "1270",
        "url": "/index.xml"
      },
      {
        "hits": "749",
        "url": "/highlight/index.xml"
      },
      {
        "hits": "693",
        "url": "/open-graph.png"
      },
      {
        "hits": "674",
        "url": "/photo/index.xml"
      },
      {
        "hits": "582",
        "url": "/post/index.xml"
      },
      {
        "hits": "576",
        "url": "/"
      },
      {
        "hits": "315",
        "url": "/css/style.css"
      },
      {
        "hits": "242",
        "url": "/favicon.png"
      },
      {
        "hits": "122",
        "url": "/post/activist-relief-resources/"
      },
      {
        "hits": "81",
        "url": "/note/"
      },
      {
        "hits": "79",
        "url": "/post/"
      },
      {
        "hits": "68",
        "url": "/articles/saved/"
      },
      {
        "hits": "58",
        "url": "/work/"
      },
      {
        "hits": "57",
        "url": "/highlight/covid-urbanist-fantasies/"
      },
      {
        "hits": "55",
        "url": "/highlight/mother-board-earth/"
      },
      {
        "hits": "55",
        "url": "/journal/"
      },
      {
        "hits": "53",
        "url": "/highlight/bring-back-blogs/"
      },
      {
        "hits": "51",
        "url": "/highlight/roxane-gay-cleaner/"
      },
      {
        "hits": "51",
        "url": "/highlight/"
      },
      {
        "hits": "49",
        "url": "/media/"
      },
      {
        "hits": "49",
        "url": "/highlight/snowden-gellman/"
      },
      {
        "hits": "49",
        "url": "/highlight/tfl-streetspace/"
      },
      {
        "hits": "49",
        "url": "/highlight/robert-pattinson/"
      },
      {
        "hits": "48",
        "url": "/highlight/chat-roulette-quar/"
      },
      {
        "hits": "48",
        "url": "/post/getting-of-of-netlify/"
      },
      {
        "hits": "45",
        "url": "/rss/"
      },
      {
        "hits": "45",
        "url": "/highlight/tulip-farm-covid/"
      },
      {
        "hits": "45",
        "url": "/highlight/american-girl-doll-history/"
      },
      {
        "hits": "45",
        "url": "/highlight/covid-flour-surge/"
      },
      {
        "hits": "45",
        "url": "/highlight/la-haine-society/"
      },
      {
        "hits": "44",
        "url": "/highlight/coronavirus-city-sound/"
      },
      {
        "hits": "43",
        "url": "/highlight/human-scale-cities/"
      },
      {
        "hits": "43",
        "url": "/highlight/trump-covid-meltdown/"
      },
      {
        "hits": "42",
        "url": "/highlight/names-gender-code/"
      },
      {
        "hits": "42",
        "url": "/highlight/london-bikes-covid/"
      },
      {
        "hits": "42",
        "url": "/highlight/ronan-farrow-too-good/"
      },
      {
        "hits": "41",
        "url": "/highlight/cessna-badass-plane/"
      },
      {
        "hits": "40",
        "url": "/highlight/mouse-feeder-welfare/"
      },
      {
        "hits": "40",
        "url": "/highlight/new-york-geology/"
      },
      {
        "hits": "38",
        "url": "/highlight/off-road-land-trains/"
      },
      {
        "hits": "38",
        "url": "/highlight/skye-covid-home/"
      },
      {
        "hits": "37",
        "url": "/highlight/samin-nosrat-eating/"
      },
      {
        "hits": "37",
        "url": "/highlight/alison-roman-culture/"
      },
      {
        "hits": "37",
        "url": "/books/reading/"
      },
      {
        "hits": "36",
        "url": "/highlight/american-police-departments/"
      },
      {
        "hits": "36",
        "url": "/analytics/day/"
      },
      {
        "hits": "36",
        "url": "/highlight/no-more-buying-stuff/"
      },
      {
        "hits": "36",
        "url": "/highlight/reading-in-the-dark/"
      },
      {
        "hits": "35",
        "url": "/highlight/ford-best-games/"
      }
    ],
    "topSiteMisses": [
      {
        "hits": "1035",
        "url": "/robots.txt"
      },
      {
        "hits": "307",
        "url": "/sw.js"
      },
      {
        "hits": "50",
        "url": "/favicon.ico"
      },
      {
        "hits": "44",
        "url": "/note/corona-nyc-hospitals/"
      },
      {
        "hits": "28",
        "url": "/note/animal-crossing-labour/"
      },
      {
        "hits": "21",
        "url": "/note/2020-04-27t104500.315z/"
      },
      {
        "hits": "20",
        "url": "/note/moses-long-island-klan/"
      },
      {
        "hits": "19",
        "url": "/jackreid.xyz/css/style.css"
      },
      {
        "hits": "15",
        "url": "/photo/ben-nevis/"
      },
      {
        "hits": "14",
        "url": "/note/dawn-or-dusk-painting/"
      },
      {
        "hits": "13",
        "url": "/wp-login.php"
      },
      {
        "hits": "12",
        "url": "/note/tech-sabbath/"
      },
      {
        "hits": "12",
        "url": "/photo/norfolk-shore/"
      },
      {
        "hits": "12",
        "url": "/note/2010-lists/"
      },
      {
        "hits": "12",
        "url": "/note/aristophanes-wasps/"
      },
      {
        "hits": "12",
        "url": "/note/roman-silphium/"
      },
      {
        "hits": "11",
        "url": "/photo/loch-lomond/"
      },
      {
        "hits": "11",
        "url": "/note/there-is-no-outside/"
      },
      {
        "hits": "10",
        "url": "/note/eugenics-statistics/"
      },
      {
        "hits": "10",
        "url": "/phpMyAdmin/scripts/setup.php"
      },
      {
        "hits": "10",
        "url": "/note/there-is-so-swing-voter/"
      },
      {
        "hits": "10",
        "url": "/note/coronavirus-central-lockdown/"
      },
      {
        "hits": "10",
        "url": "/note/carlos-williams-love/"
      },
      {
        "hits": "10",
        "url": "/note/bob-fosse/"
      },
      {
        "hits": "10",
        "url": "/note/screen-protectors/"
      },
      {
        "hits": "10",
        "url": "/note/avalanche-school/"
      },
      {
        "hits": "10",
        "url": "/note/willard-maps-of-time/"
      },
      {
        "hits": "10",
        "url": "/post/getting-of-off-netlify"
      },
      {
        "hits": "10",
        "url": "/note/james-joyce-estate/"
      },
      {
        "hits": "9",
        "url": "/note/duchy-of-cornwall/"
      },
      {
        "hits": "9",
        "url": "/note/driving-school/"
      },
      {
        "hits": "9",
        "url": "/note/precariously-balanced-rocks/"
      },
      {
        "hits": "9",
        "url": "/note/reading-difficult-books/"
      },
      {
        "hits": "9",
        "url": "/note/plath-vs-hughes/"
      },
      {
        "hits": "9",
        "url": "/note/uss-fitzgerald/"
      },
      {
        "hits": "9",
        "url": "/note/joe-biden-stutter/"
      },
      {
        "hits": "9",
        "url": "/login?from=0.000000"
      },
      {
        "hits": "9",
        "url": "/note/senate-impeachment-hamilton/"
      },
      {
        "hits": "9",
        "url": "/note/untranslatable-words/"
      },
      {
        "hits": "9",
        "url": "/phpmyadmin/scripts/setup.php"
      },
      {
        "hits": "9",
        "url": "/note/tools-i-wish-existed/"
      },
      {
        "hits": "8",
        "url": "/note/files-going-extinct/"
      },
      {
        "hits": "8",
        "url": "/note/pearshaped-magazine-archive/"
      },
      {
        "hits": "8",
        "url": "/note/rise-of-the-blur/"
      },
      {
        "hits": "8",
        "url": "/note/contrecoup/"
      },
      {
        "hits": "8",
        "url": "/note/the-great-regression/"
      },
      {
        "hits": "8",
        "url": "/photo/south-india/"
      },
      {
        "hits": "8",
        "url": "/jackreid.xyz/favicon.png"
      },
      {
        "hits": "8",
        "url": "/note/madame-tussaud/"
      },
      {
        "hits": "8",
        "url": "/photo/the-trossachs/"
      }
    ],
    "topApiHits": [
      {
        "hits": "7736",
        "url": "/pocket?limit=5000"
      },
      {
        "hits": "7736",
        "url": "/books/toread?limit=5000"
      },
      {
        "hits": "7736",
        "url": "/films/towatch?limit=5000"
      },
      {
        "hits": "7736",
        "url": "/films/watched?limit=5000"
      },
      {
        "hits": "7736",
        "url": "/articles?limit=5000"
      },
      {
        "hits": "7736",
        "url": "/books/reading?limit=5000"
      },
      {
        "hits": "7736",
        "url": "/books/read?limit=5000"
      },
      {
        "hits": "7416",
        "url": "/analytics"
      },
      {
        "hits": "30",
        "url": "/"
      },
      {
        "hits": "4",
        "url": "/books/reading"
      }
    ],
    "totalSiteHits": [
      {
        "hits": "12399"
      }
    ],
    "totalApiHits": [
      {
        "hits": "61602"
      }
    ]
  }
}
